pythonbot/Client.py
pythonbot/Errors.py
pythonbot/Message.py
pythonbot/__init__.py
pythonbot-0.5.dist-info/LICENSE
pythonbot-0.5.dist-info/METADATA
pythonbot-0.5.dist-info/WHEEL
pythonbot-0.5.dist-info/top_level.txt
pythonbot-0.5.dist-info/RECORD
