Metadata-Version: 2.1
Name: pythonbot
Version: 0.5
Summary: Simple api wrapper for Python Bot
Home-page: https://github.com/FlamptX/pythonbot-api-wrapper
Author: Flampt
License: UNKNOWN
Project-URL: Python Bot, https://python-bot.web.app
Keywords: pythonbot,api
Platform: UNKNOWN
Classifier: Programming Language :: Python :: 3
Classifier: License :: OSI Approved :: MIT License
Classifier: Operating System :: OS Independent
Requires-Python: >=3.6
